intake_omnisci/__init__.py
intake_omnisci/catalog.py
intake_omnisci/source.py
intake_omnisci-0.1.0.dist-info/LICENSE
intake_omnisci-0.1.0.dist-info/METADATA
intake_omnisci-0.1.0.dist-info/WHEEL
intake_omnisci-0.1.0.dist-info/entry_points.txt
intake_omnisci-0.1.0.dist-info/top_level.txt
intake_omnisci-0.1.0.dist-info/RECORD
