Metadata-Version: 2.1
Name: intake-omnisci
Version: 0.1.0
Summary: OmniSci plugin for Intake
Home-page: https://github.com/Quansight/intake-omnisci
Maintainer: Pearu Peterson and Ian Rose
Maintainer-email: pearu.peterson@quansight.com
License: Apache 2.0
Platform: UNKNOWN
Requires-Dist: intake (>=0.5.3)
Requires-Dist: pandas
Requires-Dist: pymapd
